potoroo/__init__.py
potoroo/_repo.py
potoroo/_uow.py
potoroo/py.typed
potoroo-0.6.0.dist-info/METADATA
potoroo-0.6.0.dist-info/WHEEL
potoroo-0.6.0.dist-info/top_level.txt
potoroo-0.6.0.dist-info/RECORD
