Metadata-Version: 2.1
Name: potoroo
Version: 0.6.0
Summary: Python implementations of the Repository and UnitOfWork abstractions.
Home-page: https://github.com/bbugyi200/potoroo
Author: Bryan M Bugyi
Author-email: bryanbugyi34@gmail.com
License: MIT license
Classifier: Development Status :: 3 - Alpha
Classifier: Intended Audience :: Developers
Classifier: License :: OSI Approved :: MIT License
Classifier: Natural Language :: English
Classifier: Programming Language :: Python :: 3
Classifier: Programming Language :: Python :: 3.9
Classifier: Programming Language :: Python :: 3.10
Classifier: Programming Language :: Python :: 3.11
Classifier: Programming Language :: Python :: 3.12
Requires-Python: >=3.9
Requires-Dist: bolton-eris ~=0.2.3
